{
  "errors": [],
  "get": "fixtures/statistics",
  "paging": {
    "current": 1,
    "total": 1
  },
  "parameters": {
    "fixture": "1351350"
  },
  "response": [
    {
      "statistics": [
        {
          "type": "Shots on Goal",
          "value": 6
        },
        {
          "type": "Shots off Goal",
          "value": 5
        },
        {
          "type": "Total Shots",
          "value": 17
        },
        {
          "type": "Blocked Shots",
          "value": 6
        },
        {
          "type": "Shots insidebox",
          "value": 13
        },
        {
          "type": "Shots outsidebox",
          "value": 4
        },
        {
          "type": "Fouls",
          "value": 11
        },
        {
          "type": "Corner Kicks",
          "value": 4
        },
        {
          "type": "Offsides",
          "value": 1
        },
        {
          "type": "Ball Possession",
          "value": "69%"
        },
        {
          "type": "Yellow Cards",
          "value": 3
        },
        {
          "type": "Red Cards",
          "value": null
        },
        {
          "type": "Goalkeeper Saves",
          "value": 2
        },
        {
          "type": "Total passes",
          "value": 535
        },
        {
          "type": "Passes accurate",
          "value": 464
        },
        {
          "type": "Passes %",
          "value": "87%"
        },
        {
          "type": "expected_goals",
          "value": "1.58"
        },
        {
          "type": "goals_prevented",
          "value": 0
        }
      ],
      "team": {
        "id": 118,
        "logo": "https://media.api-sports.io/football/teams/118.png",
        "name": "Bahia"
      }
    },
    {
      "statistics": [
        {
          "type": "Shots on Goal",
          "value": 3
        },
        {
          "type": "Shots off Goal",
          "value": 3
        },
        {
          "type": "Total Shots",
          "value": 7
        },
        {
          "type": "Blocked Shots",
          "value": 1
        },
        {
          "type": "Shots insidebox",
          "value": 5
        },
        {
          "type": "Shots outsidebox",
          "value": 2
        },
        {
          "type": "Fouls",
          "value": 20
        },
        {
          "type": "Corner Kicks",
          "value": 3
        },
        {
          "type": "Offsides",
          "value": 2
        },
        {
          "type": "Ball Possession",
          "value": "31%"
        },
        {
          "type": "Yellow Cards",
          "value": 5
        },
        {
          "type": "Red Cards",
          "value": null
        },
        {
          "type": "Goalkeeper Saves",
          "value": 4
        },
        {
          "type": "Total passes",
          "value": 232
        },
        {
          "type": "Passes accurate",
          "value": 164
        },
        {
          "type": "Passes %",
          "value": "71%"
        },
        {
          "type": "expected_goals",
          "value": "0.76"
        },
        {
          "type": "goals_prevented",
          "value": 0
        }
      ],
      "team": {
        "id": 794,
        "logo": "https://media.api-sports.io/football/teams/794.png",
        "name": "RB Bragantino"
      }
    }
  ],
  "results": 2
}